Verilog/Comparator/comparator.v
module comparator (
    input A3,A2,A1,A0,B3,B2,B1,B0,
    output g,e,l
);
    // A = B
    wire xn0,xn1,xn2,xn3;
    xnor exn1(xn0,A0,B0);
    xnor exn2(xn1,A1,B1);
    xnor exn3(xn2,A2,B2);
    xnor exn4(xn3,A3,B3);
    and a7(e,xn0,xn1,xn2,xn3);

    // A > B
    wire an0,an1,an2,an3,b0,b1,b2,b3;
    not n1(b0,B0);
    not n2(b1,B1);
    not n3(b2,B2);
    not n4(b3,B3);
    nand na1(an0,A3,b3);
    nand na2(an1,xn3,A2,b2);
    nand na3(an2,xn3,xn2,A1,b1);
    nand na4(an3,xn3,xn2,xn1,A0,b0);
    nand na5(g,an0,an1,an2,an3);

    // A < B
    nor(l,e,g);
endmodule

Verilog/Comparator/comparator_tb.v
module comparator_tb;
    reg A3,A2,A1,A0,B3,B2,B0,B1;
    wire g,e,l;

    comparator comparator_tb(A3,A2,A1,A0,B3,B2,B1,B0,g,e,l);
    initial
    begin
        $dumpfile("comparator_out.vcd");
        $dumpvars(0,comparator_tb);
        $monitor("T=%4t:A3 = %b,A2 = %b,A1 = %b,A0 = %b,B3 = %b,B2 = %b,B1 = %b,B0 = %b,g = %b, e = %b, l = %b",$time,A3,A2,A1,A0,B3,B2,B1,B0,g,e,l);
        #5 A3=0;A2=0;A1=0;A0=0;B3=0;B2=0;B1=0;B0=0;
        #5 A3=0;A2=0;A1=0;A0=0;B3=0;B2=0;B1=0;B0=1;
        #5 A3=0;A2=0;A1=0;A0=0;B3=0;B2=0;B1=1;B0=0;
        #5 A3=0;A2=0;A1=0;A0=0;B3=0;B2=0;B1=1;B0=1;
        #5 A3=0;A2=0;A1=0;A0=0;B3=0;B2=1;B1=0;B0=0;
        #5 A3=0;A2=0;A1=0;A0=0;B3=0;B2=1;B1=0;B0=1;
        #5 A3=0;A2=0;A1=0;A0=0;B3=0;B2=1;B1=1;B0=0;
        #5 A3=0;A2=0;A1=0;A0=0;B3=0;B2=1;B1=1;B0=1;
        #5 A3=0;A2=0;A1=0;A0=0;B3=1;B2=0;B1=0;B0=0;
        #5 A3=0;A2=0;A1=0;A0=0;B3=1;B2=0;B1=0;B0=1;
        #5 A3=0;A2=0;A1=0;A0=0;B3=1;B2=0;B1=1;B0=0;
        #5 A3=0;A2=0;A1=0;A0=0;B3=1;B2=0;B1=1;B0=1;
        #5 A3=0;A2=0;A1=0;A0=0;B3=1;B2=1;B1=0;B0=0;
        #5 A3=0;A2=0;A1=0;A0=0;B3=1;B2=1;B1=0;B0=1;
        #5 A3=0;A2=0;A1=0;A0=0;B3=1;B2=1;B1=1;B0=0;
        #5 A3=0;A2=0;A1=0;A0=0;B3=1;B2=1;B1=1;B0=1;
        #5 A3=0;A2=0;A1=0;A0=1;B3=0;B2=0;B1=0;B0=0;
        #5 A3=0;A2=0;A1=0;A0=1;B3=0;B2=0;B1=0;B0=1;
        #5 A3=0;A2=0;A1=0;A0=1;B3=0;B2=0;B1=1;B0=0;
        #5 A3=0;A2=0;A1=0;A0=1;B3=0;B2=0;B1=1;B0=1;
        #5 A3=0;A2=0;A1=0;A0=1;B3=0;B2=1;B1=0;B0=0;
        #5 A3=0;A2=0;A1=0;A0=1;B3=0;B2=1;B1=0;B0=1;
        #5 A3=0;A2=0;A1=0;A0=1;B3=0;B2=1;B1=1;B0=0;
        #5 A3=0;A2=0;A1=0;A0=1;B3=0;B2=1;B1=1;B0=1;
        #5 A3=0;A2=0;A1=0;A0=1;B3=1;B2=0;B1=0;B0=0;
        #5 A3=0;A2=0;A1=0;A0=1;B3=1;B2=0;B1=0;B0=1;
        #5 A3=0;A2=0;A1=0;A0=1;B3=1;B2=0;B1=1;B0=0;
        #5 A3=0;A2=0;A1=0;A0=1;B3=1;B2=0;B1=1;B0=1;
        #5 A3=0;A2=0;A1=0;A0=1;B3=1;B2=1;B1=0;B0=0;
        #5 A3=0;A2=0;A1=0;A0=1;B3=1;B2=1;B1=0;B0=1;
        #5 A3=0;A2=0;A1=0;A0=1;B3=1;B2=1;B1=1;B0=0;
        #5 A3=0;A2=0;A1=0;A0=1;B3=1;B2=1;B1=1;B0=1;
        #5 A3=0;A2=0;A1=1;A0=0;B3=0;B2=0;B1=0;B0=0;
        #5 A3=0;A2=0;A1=1;A0=0;B3=0;B2=0;B1=0;B0=1;
        #5 A3=0;A2=0;A1=1;A0=0;B3=0;B2=0;B1=1;B0=0;
        #5 A3=0;A2=0;A1=1;A0=0;B3=0;B2=0;B1=1;B0=1;
        #5 A3=0;A2=0;A1=1;A0=0;B3=0;B2=1;B1=0;B0=0;
        #5 A3=0;A2=0;A1=1;A0=0;B3=0;B2=1;B1=0;B0=1;
        #5 A3=0;A2=0;A1=1;A0=0;B3=0;B2=1;B1=1;B0=0;
        #5 A3=0;A2=0;A1=1;A0=0;B3=0;B2=1;B1=1;B0=1;
        #5 A3=0;A2=0;A1=1;A0=0;B3=1;B2=0;B1=0;B0=0;
        #5 A3=0;A2=0;A1=1;A0=0;B3=1;B2=0;B1=0;B0=1;
        #5 A3=0;A2=0;A1=1;A0=0;B3=1;B2=0;B1=1;B0=0;
        #5 A3=0;A2=0;A1=1;A0=0;B3=1;B2=0;B1=1;B0=1;
        #5 A3=0;A2=0;A1=1;A0=0;B3=1;B2=1;B1=0;B0=0;
        #5 A3=0;A2=0;A1=1;A0=0;B3=1;B2=1;B1=0;B0=1;
        #5 A3=0;A2=0;A1=1;A0=0;B3=1;B2=1;B1=1;B0=0;
        #5 A3=0;A2=0;A1=1;A0=0;B3=1;B2=1;B1=1;B0=1;
        #5 A3=0;A2=0;A1=1;A0=1;B3=0;B2=0;B1=0;B0=0;
        #5 A3=0;A2=0;A1=1;A0=1;B3=0;B2=0;B1=0;B0=1;
        #5 A3=0;A2=0;A1=1;A0=1;B3=0;B2=0;B1=1;B0=0;
        #5 A3=0;A2=0;A1=1;A0=1;B3=0;B2=0;B1=1;B0=1;
        #5 A3=0;A2=0;A1=1;A0=1;B3=0;B2=1;B1=0;B0=0;
        #5 A3=0;A2=0;A1=1;A0=1;B3=0;B2=1;B1=0;B0=1;
        #5 A3=0;A2=0;A1=1;A0=1;B3=0;B2=1;B1=1;B0=0;
        #5 A3=0;A2=0;A1=1;A0=1;B3=0;B2=1;B1=1;B0=1;
        #5 A3=0;A2=0;A1=1;A0=1;B3=1;B2=0;B1=0;B0=0;
        #5 A3=0;A2=0;A1=1;A0=1;B3=1;B2=0;B1=0;B0=1;
        #5 A3=0;A2=0;A1=1;A0=1;B3=1;B2=0;B1=1;B0=0;
        #5 A3=0;A2=0;A1=1;A0=1;B3=1;B2=0;B1=1;B0=1;
        #5 A3=0;A2=0;A1=1;A0=1;B3=1;B2=1;B1=0;B0=0;
        #5 A3=0;A2=0;A1=1;A0=1;B3=1;B2=1;B1=0;B0=1;
        #5 A3=0;A2=0;A1=1;A0=1;B3=1;B2=1;B1=1;B0=0;
        #5 A3=0;A2=0;A1=1;A0=1;B3=1;B2=1;B1=1;B0=1;
        #5 A3=0;A2=1;A1=0;A0=0;B3=0;B2=0;B1=0;B0=0;
        #5 A3=0;A2=1;A1=0;A0=0;B3=0;B2=0;B1=0;B0=1;
        #5 A3=0;A2=1;A1=0;A0=0;B3=0;B2=0;B1=1;B0=0;
        #5 A3=0;A2=1;A1=0;A0=0;B3=0;B2=0;B1=1;B0=1;
        #5 A3=0;A2=1;A1=0;A0=0;B3=0;B2=1;B1=0;B0=0;
        #5 A3=0;A2=1;A1=0;A0=0;B3=0;B2=1;B1=0;B0=1;
        #5 A3=0;A2=1;A1=0;A0=0;B3=0;B2=1;B1=1;B0=0;
        #5 A3=0;A2=1;A1=0;A0=0;B3=0;B2=1;B1=1;B0=1;
        #5 A3=0;A2=1;A1=0;A0=0;B3=1;B2=0;B1=0;B0=0;
        #5 A3=0;A2=1;A1=0;A0=0;B3=1;B2=0;B1=0;B0=1;
        #5 A3=0;A2=1;A1=0;A0=0;B3=1;B2=0;B1=1;B0=0;
        #5 A3=0;A2=1;A1=0;A0=0;B3=1;B2=0;B1=1;B0=1;
        #5 A3=0;A2=1;A1=0;A0=0;B3=1;B2=1;B1=0;B0=0;
        #5 A3=0;A2=1;A1=0;A0=0;B3=1;B2=1;B1=0;B0=1;
        #5 A3=0;A2=1;A1=0;A0=0;B3=1;B2=1;B1=1;B0=0;
        #5 A3=0;A2=1;A1=0;A0=0;B3=1;B2=1;B1=1;B0=1;
        #5 A3=0;A2=1;A1=0;A0=1;B3=0;B2=0;B1=0;B0=0;
        #5 A3=0;A2=1;A1=0;A0=1;B3=0;B2=0;B1=0;B0=1;
        #5 A3=0;A2=1;A1=0;A0=1;B3=0;B2=0;B1=1;B0=0;
        #5 A3=0;A2=1;A1=0;A0=1;B3=0;B2=0;B1=1;B0=1;
        #5 A3=0;A2=1;A1=0;A0=1;B3=0;B2=1;B1=0;B0=0;
        #5 A3=0;A2=1;A1=0;A0=1;B3=0;B2=1;B1=0;B0=1;
        #5 A3=0;A2=1;A1=0;A0=1;B3=0;B2=1;B1=1;B0=0;
        #5 A3=0;A2=1;A1=0;A0=1;B3=0;B2=1;B1=1;B0=1;
        #5 A3=0;A2=1;A1=0;A0=1;B3=1;B2=0;B1=0;B0=0;
        #5 A3=0;A2=1;A1=0;A0=1;B3=1;B2=0;B1=0;B0=1;
        #5 A3=0;A2=1;A1=0;A0=1;B3=1;B2=0;B1=1;B0=0;
        #5 A3=0;A2=1;A1=0;A0=1;B3=1;B2=0;B1=1;B0=1;
        #5 A3=0;A2=1;A1=0;A0=1;B3=1;B2=1;B1=0;B0=0;
        #5 A3=0;A2=1;A1=0;A0=1;B3=1;B2=1;B1=0;B0=1;
        #5 A3=0;A2=1;A1=0;A0=1;B3=1;B2=1;B1=1;B0=0;
        #5 A3=0;A2=1;A1=0;A0=1;B3=1;B2=1;B1=1;B0=1;
        #5 A3=0;A2=1;A1=1;A0=0;B3=0;B2=0;B1=0;B0=0;
        #5 A3=0;A2=1;A1=1;A0=0;B3=0;B2=0;B1=0;B0=1;
        #5 A3=0;A2=1;A1=1;A0=0;B3=0;B2=0;B1=1;B0=0;
        #5 A3=0;A2=1;A1=1;A0=0;B3=0;B2=0;B1=1;B0=1;
        #5 A3=0;A2=1;A1=1;A0=0;B3=0;B2=1;B1=0;B0=0;
        #5 A3=0;A2=1;A1=1;A0=0;B3=0;B2=1;B1=0;B0=1;
        #5 A3=0;A2=1;A1=1;A0=0;B3=0;B2=1;B1=1;B0=0;
        #5 A3=0;A2=1;A1=1;A0=0;B3=0;B2=1;B1=1;B0=1;
        #5 A3=0;A2=1;A1=1;A0=0;B3=1;B2=0;B1=0;B0=0;
        #5 A3=0;A2=1;A1=1;A0=0;B3=1;B2=0;B1=0;B0=1;
        #5 A3=0;A2=1;A1=1;A0=0;B3=1;B2=0;B1=1;B0=0;
        #5 A3=0;A2=1;A1=1;A0=0;B3=1;B2=0;B1=1;B0=1;
        #5 A3=0;A2=1;A1=1;A0=0;B3=1;B2=1;B1=0;B0=0;
        #5 A3=0;A2=1;A1=1;A0=0;B3=1;B2=1;B1=0;B0=1;
        #5 A3=0;A2=1;A1=1;A0=0;B3=1;B2=1;B1=1;B0=0;
        #5 A3=0;A2=1;A1=1;A0=0;B3=1;B2=1;B1=1;B0=1;
        #5 A3=0;A2=1;A1=1;A0=1;B3=0;B2=0;B1=0;B0=0;
        #5 A3=0;A2=1;A1=1;A0=1;B3=0;B2=0;B1=0;B0=1;
        #5 A3=0;A2=1;A1=1;A0=1;B3=0;B2=0;B1=1;B0=0;
        #5 A3=0;A2=1;A1=1;A0=1;B3=0;B2=0;B1=1;B0=1;
        #5 A3=0;A2=1;A1=1;A0=1;B3=0;B2=1;B1=0;B0=0;
        #5 A3=0;A2=1;A1=1;A0=1;B3=0;B2=1;B1=0;B0=1;
        #5 A3=0;A2=1;A1=1;A0=1;B3=0;B2=1;B1=1;B0=0;
        #5 A3=0;A2=1;A1=1;A0=1;B3=0;B2=1;B1=1;B0=1;
        #5 A3=0;A2=1;A1=1;A0=1;B3=1;B2=0;B1=0;B0=0;
        #5 A3=0;A2=1;A1=1;A0=1;B3=1;B2=0;B1=0;B0=1;
        #5 A3=0;A2=1;A1=1;A0=1;B3=1;B2=0;B1=1;B0=0;
        #5 A3=0;A2=1;A1=1;A0=1;B3=1;B2=0;B1=1;B0=1;
        #5 A3=0;A2=1;A1=1;A0=1;B3=1;B2=1;B1=0;B0=0;
        #5 A3=0;A2=1;A1=1;A0=1;B3=1;B2=1;B1=0;B0=1;
        #5 A3=0;A2=1;A1=1;A0=1;B3=1;B2=1;B1=1;B0=0;
        #5 A3=0;A2=1;A1=1;A0=1;B3=1;B2=1;B1=1;B0=1;
        #5 A3=1;A2=0;A1=0;A0=0;B3=0;B2=0;B1=0;B0=0;
        #5 A3=1;A2=0;A1=0;A0=0;B3=0;B2=0;B1=0;B0=1;
        #5 A3=1;A2=0;A1=0;A0=0;B3=0;B2=0;B1=1;B0=0;
        #5 A3=1;A2=0;A1=0;A0=0;B3=0;B2=0;B1=1;B0=1;
        #5 A3=1;A2=0;A1=0;A0=0;B3=0;B2=1;B1=0;B0=0;
        #5 A3=1;A2=0;A1=0;A0=0;B3=0;B2=1;B1=0;B0=1;
        #5 A3=1;A2=0;A1=0;A0=0;B3=0;B2=1;B1=1;B0=0;
        #5 A3=1;A2=0;A1=0;A0=0;B3=0;B2=1;B1=1;B0=1;
        #5 A3=1;A2=0;A1=0;A0=0;B3=1;B2=0;B1=0;B0=0;
        #5 A3=1;A2=0;A1=0;A0=0;B3=1;B2=0;B1=0;B0=1;
        #5 A3=1;A2=0;A1=0;A0=0;B3=1;B2=0;B1=1;B0=0;
        #5 A3=1;A2=0;A1=0;A0=0;B3=1;B2=0;B1=1;B0=1;
        #5 A3=1;A2=0;A1=0;A0=0;B3=1;B2=1;B1=0;B0=0;
        #5 A3=1;A2=0;A1=0;A0=0;B3=1;B2=1;B1=0;B0=1;
        #5 A3=1;A2=0;A1=0;A0=0;B3=1;B2=1;B1=1;B0=0;
        #5 A3=1;A2=0;A1=0;A0=0;B3=1;B2=1;B1=1;B0=1;
        #5 A3=1;A2=0;A1=0;A0=1;B3=0;B2=0;B1=0;B0=0;
        #5 A3=1;A2=0;A1=0;A0=1;B3=0;B2=0;B1=0;B0=1;
        #5 A3=1;A2=0;A1=0;A0=1;B3=0;B2=0;B1=1;B0=0;
        #5 A3=1;A2=0;A1=0;A0=1;B3=0;B2=0;B1=1;B0=1;
        #5 A3=1;A2=0;A1=0;A0=1;B3=0;B2=1;B1=0;B0=0;
        #5 A3=1;A2=0;A1=0;A0=1;B3=0;B2=1;B1=0;B0=1;
        #5 A3=1;A2=0;A1=0;A0=1;B3=0;B2=1;B1=1;B0=0;
        #5 A3=1;A2=0;A1=0;A0=1;B3=0;B2=1;B1=1;B0=1;
        #5 A3=1;A2=0;A1=0;A0=1;B3=1;B2=0;B1=0;B0=0;
        #5 A3=1;A2=0;A1=0;A0=1;B3=1;B2=0;B1=0;B0=1;
        #5 A3=1;A2=0;A1=0;A0=1;B3=1;B2=0;B1=1;B0=0;
        #5 A3=1;A2=0;A1=0;A0=1;B3=1;B2=0;B1=1;B0=1;
        #5 A3=1;A2=0;A1=0;A0=1;B3=1;B2=1;B1=0;B0=0;
        #5 A3=1;A2=0;A1=0;A0=1;B3=1;B2=1;B1=0;B0=1;
        #5 A3=1;A2=0;A1=0;A0=1;B3=1;B2=1;B1=1;B0=0;
        #5 A3=1;A2=0;A1=0;A0=1;B3=1;B2=1;B1=1;B0=1;
        #5 A3=1;A2=0;A1=1;A0=0;B3=0;B2=0;B1=0;B0=0;
        #5 A3=1;A2=0;A1=1;A0=0;B3=0;B2=0;B1=0;B0=1;
        #5 A3=1;A2=0;A1=1;A0=0;B3=0;B2=0;B1=1;B0=0;
        #5 A3=1;A2=0;A1=1;A0=0;B3=0;B2=0;B1=1;B0=1;
        #5 A3=1;A2=0;A1=1;A0=0;B3=0;B2=1;B1=0;B0=0;
        #5 A3=1;A2=0;A1=1;A0=0;B3=0;B2=1;B1=0;B0=1;
        #5 A3=1;A2=0;A1=1;A0=0;B3=0;B2=1;B1=1;B0=0;
        #5 A3=1;A2=0;A1=1;A0=0;B3=0;B2=1;B1=1;B0=1;
        #5 A3=1;A2=0;A1=1;A0=0;B3=1;B2=0;B1=0;B0=0;
        #5 A3=1;A2=0;A1=1;A0=0;B3=1;B2=0;B1=0;B0=1;
        #5 A3=1;A2=0;A1=1;A0=0;B3=1;B2=0;B1=1;B0=0;
        #5 A3=1;A2=0;A1=1;A0=0;B3=1;B2=0;B1=1;B0=1;
        #5 A3=1;A2=0;A1=1;A0=0;B3=1;B2=1;B1=0;B0=0;
        #5 A3=1;A2=0;A1=1;A0=0;B3=1;B2=1;B1=0;B0=1;
        #5 A3=1;A2=0;A1=1;A0=0;B3=1;B2=1;B1=1;B0=0;
        #5 A3=1;A2=0;A1=1;A0=0;B3=1;B2=1;B1=1;B0=1;
        #5 A3=1;A2=0;A1=1;A0=1;B3=0;B2=0;B1=0;B0=0;
        #5 A3=1;A2=0;A1=1;A0=1;B3=0;B2=0;B1=0;B0=1;
        #5 A3=1;A2=0;A1=1;A0=1;B3=0;B2=0;B1=1;B0=0;
        #5 A3=1;A2=0;A1=1;A0=1;B3=0;B2=0;B1=1;B0=1;
        #5 A3=1;A2=0;A1=1;A0=1;B3=0;B2=1;B1=0;B0=0;
        #5 A3=1;A2=0;A1=1;A0=1;B3=0;B2=1;B1=0;B0=1;
        #5 A3=1;A2=0;A1=1;A0=1;B3=0;B2=1;B1=1;B0=0;
        #5 A3=1;A2=0;A1=1;A0=1;B3=0;B2=1;B1=1;B0=1;
        #5 A3=1;A2=0;A1=1;A0=1;B3=1;B2=0;B1=0;B0=0;
        #5 A3=1;A2=0;A1=1;A0=1;B3=1;B2=0;B1=0;B0=1;
        #5 A3=1;A2=0;A1=1;A0=1;B3=1;B2=0;B1=1;B0=0;
        #5 A3=1;A2=0;A1=1;A0=1;B3=1;B2=0;B1=1;B0=1;
        #5 A3=1;A2=0;A1=1;A0=1;B3=1;B2=1;B1=0;B0=0;
        #5 A3=1;A2=0;A1=1;A0=1;B3=1;B2=1;B1=0;B0=1;
        #5 A3=1;A2=0;A1=1;A0=1;B3=1;B2=1;B1=1;B0=0;
        #5 A3=1;A2=0;A1=1;A0=1;B3=1;B2=1;B1=1;B0=1;
        #5 A3=1;A2=1;A1=0;A0=0;B3=0;B2=0;B1=0;B0=0;
        #5 A3=1;A2=1;A1=0;A0=0;B3=0;B2=0;B1=0;B0=1;
        #5 A3=1;A2=1;A1=0;A0=0;B3=0;B2=0;B1=1;B0=0;
        #5 A3=1;A2=1;A1=0;A0=0;B3=0;B2=0;B1=1;B0=1;
        #5 A3=1;A2=1;A1=0;A0=0;B3=0;B2=1;B1=0;B0=0;
        #5 A3=1;A2=1;A1=0;A0=0;B3=0;B2=1;B1=0;B0=1;
        #5 A3=1;A2=1;A1=0;A0=0;B3=0;B2=1;B1=1;B0=0;
        #5 A3=1;A2=1;A1=0;A0=0;B3=0;B2=1;B1=1;B0=1;
        #5 A3=1;A2=1;A1=0;A0=0;B3=1;B2=0;B1=0;B0=0;
        #5 A3=1;A2=1;A1=0;A0=0;B3=1;B2=0;B1=0;B0=1;
        #5 A3=1;A2=1;A1=0;A0=0;B3=1;B2=0;B1=1;B0=0;
        #5 A3=1;A2=1;A1=0;A0=0;B3=1;B2=0;B1=1;B0=1;
        #5 A3=1;A2=1;A1=0;A0=0;B3=1;B2=1;B1=0;B0=0;
        #5 A3=1;A2=1;A1=0;A0=0;B3=1;B2=1;B1=0;B0=1;
        #5 A3=1;A2=1;A1=0;A0=0;B3=1;B2=1;B1=1;B0=0;
        #5 A3=1;A2=1;A1=0;A0=0;B3=1;B2=1;B1=1;B0=1;
        #5 A3=1;A2=1;A1=0;A0=1;B3=0;B2=0;B1=0;B0=0;
        #5 A3=1;A2=1;A1=0;A0=1;B3=0;B2=0;B1=0;B0=1;
        #5 A3=1;A2=1;A1=0;A0=1;B3=0;B2=0;B1=1;B0=0;
        #5 A3=1;A2=1;A1=0;A0=1;B3=0;B2=0;B1=1;B0=1;
        #5 A3=1;A2=1;A1=0;A0=1;B3=0;B2=1;B1=0;B0=0;
        #5 A3=1;A2=1;A1=0;A0=1;B3=0;B2=1;B1=0;B0=1;
        #5 A3=1;A2=1;A1=0;A0=1;B3=0;B2=1;B1=1;B0=0;
        #5 A3=1;A2=1;A1=0;A0=1;B3=0;B2=1;B1=1;B0=1;
        #5 A3=1;A2=1;A1=0;A0=1;B3=1;B2=0;B1=0;B0=0;
        #5 A3=1;A2=1;A1=0;A0=1;B3=1;B2=0;B1=0;B0=1;
        #5 A3=1;A2=1;A1=0;A0=1;B3=1;B2=0;B1=1;B0=0;
        #5 A3=1;A2=1;A1=0;A0=1;B3=1;B2=0;B1=1;B0=1;
        #5 A3=1;A2=1;A1=0;A0=1;B3=1;B2=1;B1=0;B0=0;
        #5 A3=1;A2=1;A1=0;A0=1;B3=1;B2=1;B1=0;B0=1;
        #5 A3=1;A2=1;A1=0;A0=1;B3=1;B2=1;B1=1;B0=0;
        #5 A3=1;A2=1;A1=0;A0=1;B3=1;B2=1;B1=1;B0=1;
        #5 A3=1;A2=1;A1=1;A0=0;B3=0;B2=0;B1=0;B0=0;
        #5 A3=1;A2=1;A1=1;A0=0;B3=0;B2=0;B1=0;B0=1;
        #5 A3=1;A2=1;A1=1;A0=0;B3=0;B2=0;B1=1;B0=0;
        #5 A3=1;A2=1;A1=1;A0=0;B3=0;B2=0;B1=1;B0=1;
        #5 A3=1;A2=1;A1=1;A0=0;B3=0;B2=1;B1=0;B0=0;
        #5 A3=1;A2=1;A1=1;A0=0;B3=0;B2=1;B1=0;B0=1;
        #5 A3=1;A2=1;A1=1;A0=0;B3=0;B2=1;B1=1;B0=0;
        #5 A3=1;A2=1;A1=1;A0=0;B3=0;B2=1;B1=1;B0=1;
        #5 A3=1;A2=1;A1=1;A0=0;B3=1;B2=0;B1=0;B0=0;
        #5 A3=1;A2=1;A1=1;A0=0;B3=1;B2=0;B1=0;B0=1;
        #5 A3=1;A2=1;A1=1;A0=0;B3=1;B2=0;B1=1;B0=0;
        #5 A3=1;A2=1;A1=1;A0=0;B3=1;B2=0;B1=1;B0=1;
        #5 A3=1;A2=1;A1=1;A0=0;B3=1;B2=1;B1=0;B0=0;
        #5 A3=1;A2=1;A1=1;A0=0;B3=1;B2=1;B1=0;B0=1;
        #5 A3=1;A2=1;A1=1;A0=0;B3=1;B2=1;B1=1;B0=0;
        #5 A3=1;A2=1;A1=1;A0=0;B3=1;B2=1;B1=1;B0=1;
        #5 A3=1;A2=1;A1=1;A0=1;B3=0;B2=0;B1=0;B0=0;
        #5 A3=1;A2=1;A1=1;A0=1;B3=0;B2=0;B1=0;B0=1;
        #5 A3=1;A2=1;A1=1;A0=1;B3=0;B2=0;B1=1;B0=0;
        #5 A3=1;A2=1;A1=1;A0=1;B3=0;B2=0;B1=1;B0=1;
        #5 A3=1;A2=1;A1=1;A0=1;B3=0;B2=1;B1=0;B0=0;
        #5 A3=1;A2=1;A1=1;A0=1;B3=0;B2=1;B1=0;B0=1;
        #5 A3=1;A2=1;A1=1;A0=1;B3=0;B2=1;B1=1;B0=0;
        #5 A3=1;A2=1;A1=1;A0=1;B3=0;B2=1;B1=1;B0=1;
        #5 A3=1;A2=1;A1=1;A0=1;B3=1;B2=0;B1=0;B0=0;
        #5 A3=1;A2=1;A1=1;A0=1;B3=1;B2=0;B1=0;B0=1;
        #5 A3=1;A2=1;A1=1;A0=1;B3=1;B2=0;B1=1;B0=0;
        #5 A3=1;A2=1;A1=1;A0=1;B3=1;B2=0;B1=1;B0=1;
        #5 A3=1;A2=1;A1=1;A0=1;B3=1;B2=1;B1=0;B0=0;
        #5 A3=1;A2=1;A1=1;A0=1;B3=1;B2=1;B1=0;B0=1;
        #5 A3=1;A2=1;A1=1;A0=1;B3=1;B2=1;B1=1;B0=0;
        #5 A3=1;A2=1;A1=1;A0=1;B3=1;B2=1;B1=1;B0=1;
        #5 $finish;
    end 
endmodule

Verilog/Comparator/comparator_out.vcd
$date
	Fri Oct 27 11:45:06 2023
$end
$version
	Icarus Verilog
$end
$timescale
	1s
$end
$scope module comparator_tb $end
$scope module comparator_tb $end
$var wire 1 ! A0 $end
$var wire 1 " A1 $end
$var wire 1 # A2 $end
$var wire 1 $ A3 $end
$var wire 1 % B0 $end
$var wire 1 & B1 $end
$var wire 1 ' B2 $end
$var wire 1 ( B3 $end
$var wire 1 ) an0 $end
$var wire 1 * an1 $end
$var wire 1 + an2 $end
$var wire 1 , an3 $end
$var wire 1 - b0 $end
$var wire 1 . b1 $end
$var wire 1 / b2 $end
$var wire 1 0 b3 $end
$var wire 1 1 e $end
$var wire 1 2 g $end
$var wire 1 3 l $end
$var wire 1 4 xn0 $end
$var wire 1 5 xn1 $end
$var wire 1 6 xn2 $end
$var wire 1 7 xn3 $end
$upscope $end
$upscope $end
$enddefinitions $end
#0
$dumpvars
x7
x6
x5
x4
x3
x2
x1
x0
x/
x.
x-
x,
x+
x*
x)
x(
x'
x&
x%
x$
x#
x"
x!
$end
#5
02
03
0,
11
1-
1.
1/
10
14
15
0+
16
0*
17
0)
0%
0&
0'
0(
0!
0"
0#
0$
#10
13
01
04
0-
1%
#15
14
1-
05
0.
0%
1&
#20
04
0-
1%
#25
14
1-
15
1.
06
0/
0%
0&
1'
#30
04
0-
1%
#35
14
1-
05
0.
0%
1&
#40
04
0-
1%
#45
14
1-
15
1.
16
1/
07
00
0%
0&
0'
1(
#50
04
0-
1%
#55
14
1-
05
0.
0%
1&
#60
04
0-
1%
#65
14
1-
15
1.
06
0/
0%
0&
1'
#70
04
0-
1%
#75
14
1-
05
0.
0%
1&
#80
04
0-
1%
#85
03
12
1,
1-
15
1.
16
1/
17
10
0%
0&
0'
0(
1!
#90
02
0,
11
14
0-
1%
#95
13
01
04
1-
05
0.
0%
1&
#100
14
0-
1%
#105
04
1-
15
1.
06
0/
0%
0&
1'
#110
14
0-
1%
#115
04
1-
05
0.
0%
1&
#120
14
0-
1%
#125
04
1-
15
1.
16
1/
07
00
0%
0&
0'
1(
#130
14
0-
1%
#135
04
1-
05
0.
0%
1&
#140
14
0-
1%
#145
04
1-
15
1.
06
0/
0%
0&
1'
#150
14
0-
1%
#155
04
1-
05
0.
0%
1&
#160
14
0-
1%
#165
03
12
1+
1-
1.
16
1/
17
10
0%
0&
0'
0(
0!
1"
#170
04
0-
1%
#175
02
11
0+
14
1-
15
0.
0%
1&
#180
13
01
04
0-
1%
#185
14
1-
05
1.
06
0/
0%
0&
1'
#190
04
0-
1%
#195
14
1-
15
0.
0%
1&
#200
04
0-
1%
#205
14
1-
05
1.
16
1/
07
00
0%
0&
0'
1(
#210
04
0-
1%
#215
14
1-
15
0.
0%
1&
#220
04
0-
1%
#225
14
1-
05
1.
06
0/
0%
0&
1'
#230
04
0-
1%
#235
14
1-
15
0.
0%
1&
#240
04
0-
1%
#245
03
12
1+
1-
05
1.
16
1/
17
10
0%
0&
0'
0(
1!
#250
14
0-
1%
#255
03
1,
12
0+
04
1-
15
0.
0%
1&
#260
02
0,
11
14
0-
1%
#265
13
01
04
1-
05
1.
06
0/
0%
0&
1'
#270
14
0-
1%
#275
04
1-
15
0.
0%
1&
#280
14
0-
1%
#285
04
1-
05
1.
16
1/
07
00
0%
0&
0'
1(
#290
14
0-
1%
#295
04
1-
15
0.
0%
1&
#300
14
0-
1%
#305
04
1-
05
1.
06
0/
0%
0&
1'
#310
14
0-
1%
#315
04
1-
15
0.
0%
1&
#320
14
0-
1%
#325
03
12
1*
1-
1.
1/
17
10
0%
0&
0'
0(
0!
0"
1#
#330
04
0-
1%
#335
14
1-
05
0.
0%
1&
#340
04
0-
1%
#345
02
11
0*
14
1-
15
1.
16
0/
0%
0&
1'
#350
13
01
04
0-
1%
#355
14
1-
05
0.
0%
1&
#360
04
0-
1%
#365
14
1-
15
1.
06
1/
07
00
0%
0&
0'
1(
#370
04
0-
1%
#375
14
1-
05
0.
0%
1&
#380
04
0-
1%
#385
14
1-
15
1.
16
0/
0%
0&
1'
#390
04
0-
1%
#395
14
1-
05
0.
0%
1&
#400
04
0-
1%
#405
03
12
1*
1-
15
1.
06
1/
17
10
0%
0&
0'
0(
1!
#410
14
0-
1%
#415
04
1-
05
0.
0%
1&
#420
14
0-
1%
#425
03
1,
12
0*
04
1-
15
1.
16
0/
0%
0&
1'
#430
02
0,
11
14
0-
1%
#435
13
01
04
1-
05
0.
0%
1&
#440
14
0-
1%
#445
04
1-
15
1.
06
1/
07
00
0%
0&
0'
1(
#450
14
0-
1%
#455
04
1-
05
0.
0%
1&
#460
14
0-
1%
#465
04
1-
15
1.
16
0/
0%
0&
1'
#470
14
0-
1%
#475
04
1-
05
0.
0%
1&
#480
14
0-
1%
#485
03
12
1*
1-
1.
06
1/
17
10
0%
0&
0'
0(
0!
1"
#490
04
0-
1%
#495
14
1-
15
0.
0%
1&
#500
04
0-
1%
#505
1+
0*
14
1-
05
1.
16
0/
0%
0&
1'
#510
04
0-
1%
#515
02
11
0+
14
1-
15
0.
0%
1&
#520
13
01
04
0-
1%
#525
14
1-
05
1.
06
1/
07
00
0%
0&
0'
1(
#530
04
0-
1%
#535
14
1-
15
0.
0%
1&
#540
04
0-
1%
#545
14
1-
05
1.
16
0/
0%
0&
1'
#550
04
0-
1%
#555
14
1-
15
0.
0%
1&
#560
04
0-
1%
#565
03
12
1*
1-
05
1.
06
1/
17
10
0%
0&
0'
0(
1!
#570
14
0-
1%
#575
04
1-
15
0.
0%
1&
