Verilog/AND/and_4bit.v
module and_4bit (
    input A3,A2,A1,A0,B3,B2,B1,B0,
    output out3,out2,out1,out0
);

    and a1(out0,A0,B0);
    and a2(out1,A1,B1);
    and a3(out2,A2,B2);
    and a4(out3,A3,B3);

endmodule

Verilog/AND/and_4bit_tb.v
module and_4bit_tb;
    reg A3,A2,A1,A0,B3,B2,B0,B1;
    wire out3,out2,out1,out0;

    and_4bit and_4bit_tb(A3,A2,A1,A0,B3,B2,B1,B0,out3,out2,out1,out0);
    initial
    begin
        $dumpfile("and_4bit_out.vcd");
        $dumpvars(0,and_4bit_tb);
        $monitor("T=%4t:A3 = %b,A2 = %b,A1 = %b,A0 = %b,B3 = %b,B2 = %b,B1 = %b,B0 = %b, out3 = %b, out2 = %b, out1 = %b, out0 = %b",$time,A3,A2,A1,A0,B3,B2,B1,B0,out3,out2,out1,out0);
        #5 A3=0;A2=0;A1=0;A0=0;B3=0;B2=0;B1=0;B0=0;
        #5 A3=0;A2=0;A1=0;A0=0;B3=0;B2=0;B1=0;B0=1;
        #5 A3=0;A2=0;A1=0;A0=0;B3=0;B2=0;B1=1;B0=0;
        #5 A3=0;A2=0;A1=0;A0=0;B3=0;B2=0;B1=1;B0=1;
        #5 A3=0;A2=0;A1=0;A0=0;B3=0;B2=1;B1=0;B0=0;
        #5 A3=0;A2=0;A1=0;A0=0;B3=0;B2=1;B1=0;B0=1;
        #5 A3=0;A2=0;A1=0;A0=0;B3=0;B2=1;B1=1;B0=0;
        #5 A3=0;A2=0;A1=0;A0=0;B3=0;B2=1;B1=1;B0=1;
        #5 A3=0;A2=0;A1=0;A0=0;B3=1;B2=0;B1=0;B0=0;
        #5 A3=0;A2=0;A1=0;A0=0;B3=1;B2=0;B1=0;B0=1;
        #5 A3=0;A2=0;A1=0;A0=0;B3=1;B2=0;B1=1;B0=0;
        #5 A3=0;A2=0;A1=0;A0=0;B3=1;B2=0;B1=1;B0=1;
        #5 A3=0;A2=0;A1=0;A0=0;B3=1;B2=1;B1=0;B0=0;
        #5 A3=0;A2=0;A1=0;A0=0;B3=1;B2=1;B1=0;B0=1;
        #5 A3=0;A2=0;A1=0;A0=0;B3=1;B2=1;B1=1;B0=0;
        #5 A3=0;A2=0;A1=0;A0=0;B3=1;B2=1;B1=1;B0=1;
        #5 A3=0;A2=0;A1=0;A0=1;B3=0;B2=0;B1=0;B0=0;
        #5 A3=0;A2=0;A1=0;A0=1;B3=0;B2=0;B1=0;B0=1;
        #5 A3=0;A2=0;A1=0;A0=1;B3=0;B2=0;B1=1;B0=0;
        #5 A3=0;A2=0;A1=0;A0=1;B3=0;B2=0;B1=1;B0=1;
        #5 A3=0;A2=0;A1=0;A0=1;B3=0;B2=1;B1=0;B0=0;
        #5 A3=0;A2=0;A1=0;A0=1;B3=0;B2=1;B1=0;B0=1;
        #5 A3=0;A2=0;A1=0;A0=1;B3=0;B2=1;B1=1;B0=0;
        #5 A3=0;A2=0;A1=0;A0=1;B3=0;B2=1;B1=1;B0=1;
        #5 A3=0;A2=0;A1=0;A0=1;B3=1;B2=0;B1=0;B0=0;
        #5 A3=0;A2=0;A1=0;A0=1;B3=1;B2=0;B1=0;B0=1;
        #5 A3=0;A2=0;A1=0;A0=1;B3=1;B2=0;B1=1;B0=0;
        #5 A3=0;A2=0;A1=0;A0=1;B3=1;B2=0;B1=1;B0=1;
        #5 A3=0;A2=0;A1=0;A0=1;B3=1;B2=1;B1=0;B0=0;
        #5 A3=0;A2=0;A1=0;A0=1;B3=1;B2=1;B1=0;B0=1;
        #5 A3=0;A2=0;A1=0;A0=1;B3=1;B2=1;B1=1;B0=0;
        #5 A3=0;A2=0;A1=0;A0=1;B3=1;B2=1;B1=1;B0=1;
        #5 A3=0;A2=0;A1=1;A0=0;B3=0;B2=0;B1=0;B0=0;
        #5 A3=0;A2=0;A1=1;A0=0;B3=0;B2=0;B1=0;B0=1;
        #5 A3=0;A2=0;A1=1;A0=0;B3=0;B2=0;B1=1;B0=0;
        #5 A3=0;A2=0;A1=1;A0=0;B3=0;B2=0;B1=1;B0=1;
        #5 A3=0;A2=0;A1=1;A0=0;B3=0;B2=1;B1=0;B0=0;
        #5 A3=0;A2=0;A1=1;A0=0;B3=0;B2=1;B1=0;B0=1;
        #5 A3=0;A2=0;A1=1;A0=0;B3=0;B2=1;B1=1;B0=0;
        #5 A3=0;A2=0;A1=1;A0=0;B3=0;B2=1;B1=1;B0=1;
        #5 A3=0;A2=0;A1=1;A0=0;B3=1;B2=0;B1=0;B0=0;
        #5 A3=0;A2=0;A1=1;A0=0;B3=1;B2=0;B1=0;B0=1;
        #5 A3=0;A2=0;A1=1;A0=0;B3=1;B2=0;B1=1;B0=0;
        #5 A3=0;A2=0;A1=1;A0=0;B3=1;B2=0;B1=1;B0=1;
        #5 A3=0;A2=0;A1=1;A0=0;B3=1;B2=1;B1=0;B0=0;
        #5 A3=0;A2=0;A1=1;A0=0;B3=1;B2=1;B1=0;B0=1;
        #5 A3=0;A2=0;A1=1;A0=0;B3=1;B2=1;B1=1;B0=0;
        #5 A3=0;A2=0;A1=1;A0=0;B3=1;B2=1;B1=1;B0=1;
        #5 A3=0;A2=0;A1=1;A0=1;B3=0;B2=0;B1=0;B0=0;
        #5 A3=0;A2=0;A1=1;A0=1;B3=0;B2=0;B1=0;B0=1;
        #5 A3=0;A2=0;A1=1;A0=1;B3=0;B2=0;B1=1;B0=0;
        #5 A3=0;A2=0;A1=1;A0=1;B3=0;B2=0;B1=1;B0=1;
        #5 A3=0;A2=0;A1=1;A0=1;B3=0;B2=1;B1=0;B0=0;
        #5 A3=0;A2=0;A1=1;A0=1;B3=0;B2=1;B1=0;B0=1;
        #5 A3=0;A2=0;A1=1;A0=1;B3=0;B2=1;B1=1;B0=0;
        #5 A3=0;A2=0;A1=1;A0=1;B3=0;B2=1;B1=1;B0=1;
        #5 A3=0;A2=0;A1=1;A0=1;B3=1;B2=0;B1=0;B0=0;
        #5 A3=0;A2=0;A1=1;A0=1;B3=1;B2=0;B1=0;B0=1;
        #5 A3=0;A2=0;A1=1;A0=1;B3=1;B2=0;B1=1;B0=0;
        #5 A3=0;A2=0;A1=1;A0=1;B3=1;B2=0;B1=1;B0=1;
        #5 A3=0;A2=0;A1=1;A0=1;B3=1;B2=1;B1=0;B0=0;
        #5 A3=0;A2=0;A1=1;A0=1;B3=1;B2=1;B1=0;B0=1;
        #5 A3=0;A2=0;A1=1;A0=1;B3=1;B2=1;B1=1;B0=0;
        #5 A3=0;A2=0;A1=1;A0=1;B3=1;B2=1;B1=1;B0=1;
        #5 A3=0;A2=1;A1=0;A0=0;B3=0;B2=0;B1=0;B0=0;
        #5 A3=0;A2=1;A1=0;A0=0;B3=0;B2=0;B1=0;B0=1;
        #5 A3=0;A2=1;A1=0;A0=0;B3=0;B2=0;B1=1;B0=0;
        #5 A3=0;A2=1;A1=0;A0=0;B3=0;B2=0;B1=1;B0=1;
        #5 A3=0;A2=1;A1=0;A0=0;B3=0;B2=1;B1=0;B0=0;
        #5 A3=0;A2=1;A1=0;A0=0;B3=0;B2=1;B1=0;B0=1;
        #5 A3=0;A2=1;A1=0;A0=0;B3=0;B2=1;B1=1;B0=0;
        #5 A3=0;A2=1;A1=0;A0=0;B3=0;B2=1;B1=1;B0=1;
        #5 A3=0;A2=1;A1=0;A0=0;B3=1;B2=0;B1=0;B0=0;
        #5 A3=0;A2=1;A1=0;A0=0;B3=1;B2=0;B1=0;B0=1;
        #5 A3=0;A2=1;A1=0;A0=0;B3=1;B2=0;B1=1;B0=0;
        #5 A3=0;A2=1;A1=0;A0=0;B3=1;B2=0;B1=1;B0=1;
        #5 A3=0;A2=1;A1=0;A0=0;B3=1;B2=1;B1=0;B0=0;
        #5 A3=0;A2=1;A1=0;A0=0;B3=1;B2=1;B1=0;B0=1;
        #5 A3=0;A2=1;A1=0;A0=0;B3=1;B2=1;B1=1;B0=0;
        #5 A3=0;A2=1;A1=0;A0=0;B3=1;B2=1;B1=1;B0=1;
        #5 A3=0;A2=1;A1=0;A0=1;B3=0;B2=0;B1=0;B0=0;
        #5 A3=0;A2=1;A1=0;A0=1;B3=0;B2=0;B1=0;B0=1;
        #5 A3=0;A2=1;A1=0;A0=1;B3=0;B2=0;B1=1;B0=0;
        #5 A3=0;A2=1;A1=0;A0=1;B3=0;B2=0;B1=1;B0=1;
        #5 A3=0;A2=1;A1=0;A0=1;B3=0;B2=1;B1=0;B0=0;
        #5 A3=0;A2=1;A1=0;A0=1;B3=0;B2=1;B1=0;B0=1;
        #5 A3=0;A2=1;A1=0;A0=1;B3=0;B2=1;B1=1;B0=0;
        #5 A3=0;A2=1;A1=0;A0=1;B3=0;B2=1;B1=1;B0=1;
        #5 A3=0;A2=1;A1=0;A0=1;B3=1;B2=0;B1=0;B0=0;
        #5 A3=0;A2=1;A1=0;A0=1;B3=1;B2=0;B1=0;B0=1;
        #5 A3=0;A2=1;A1=0;A0=1;B3=1;B2=0;B1=1;B0=0;
        #5 A3=0;A2=1;A1=0;A0=1;B3=1;B2=0;B1=1;B0=1;
        #5 A3=0;A2=1;A1=0;A0=1;B3=1;B2=1;B1=0;B0=0;
        #5 A3=0;A2=1;A1=0;A0=1;B3=1;B2=1;B1=0;B0=1;
        #5 A3=0;A2=1;A1=0;A0=1;B3=1;B2=1;B1=1;B0=0;
        #5 A3=0;A2=1;A1=0;A0=1;B3=1;B2=1;B1=1;B0=1;
        #5 A3=0;A2=1;A1=1;A0=0;B3=0;B2=0;B1=0;B0=0;
        #5 A3=0;A2=1;A1=1;A0=0;B3=0;B2=0;B1=0;B0=1;
        #5 A3=0;A2=1;A1=1;A0=0;B3=0;B2=0;B1=1;B0=0;
        #5 A3=0;A2=1;A1=1;A0=0;B3=0;B2=0;B1=1;B0=1;
        #5 A3=0;A2=1;A1=1;A0=0;B3=0;B2=1;B1=0;B0=0;
        #5 A3=0;A2=1;A1=1;A0=0;B3=0;B2=1;B1=0;B0=1;
        #5 A3=0;A2=1;A1=1;A0=0;B3=0;B2=1;B1=1;B0=0;
        #5 A3=0;A2=1;A1=1;A0=0;B3=0;B2=1;B1=1;B0=1;
        #5 A3=0;A2=1;A1=1;A0=0;B3=1;B2=0;B1=0;B0=0;
        #5 A3=0;A2=1;A1=1;A0=0;B3=1;B2=0;B1=0;B0=1;
        #5 A3=0;A2=1;A1=1;A0=0;B3=1;B2=0;B1=1;B0=0;
        #5 A3=0;A2=1;A1=1;A0=0;B3=1;B2=0;B1=1;B0=1;
        #5 A3=0;A2=1;A1=1;A0=0;B3=1;B2=1;B1=0;B0=0;
        #5 A3=0;A2=1;A1=1;A0=0;B3=1;B2=1;B1=0;B0=1;
        #5 A3=0;A2=1;A1=1;A0=0;B3=1;B2=1;B1=1;B0=0;
        #5 A3=0;A2=1;A1=1;A0=0;B3=1;B2=1;B1=1;B0=1;
        #5 A3=0;A2=1;A1=1;A0=1;B3=0;B2=0;B1=0;B0=0;
        #5 A3=0;A2=1;A1=1;A0=1;B3=0;B2=0;B1=0;B0=1;
        #5 A3=0;A2=1;A1=1;A0=1;B3=0;B2=0;B1=1;B0=0;
        #5 A3=0;A2=1;A1=1;A0=1;B3=0;B2=0;B1=1;B0=1;
        #5 A3=0;A2=1;A1=1;A0=1;B3=0;B2=1;B1=0;B0=0;
        #5 A3=0;A2=1;A1=1;A0=1;B3=0;B2=1;B1=0;B0=1;
        #5 A3=0;A2=1;A1=1;A0=1;B3=0;B2=1;B1=1;B0=0;
        #5 A3=0;A2=1;A1=1;A0=1;B3=0;B2=1;B1=1;B0=1;
        #5 A3=0;A2=1;A1=1;A0=1;B3=1;B2=0;B1=0;B0=0;
        #5 A3=0;A2=1;A1=1;A0=1;B3=1;B2=0;B1=0;B0=1;
        #5 A3=0;A2=1;A1=1;A0=1;B3=1;B2=0;B1=1;B0=0;
        #5 A3=0;A2=1;A1=1;A0=1;B3=1;B2=0;B1=1;B0=1;
        #5 A3=0;A2=1;A1=1;A0=1;B3=1;B2=1;B1=0;B0=0;
        #5 A3=0;A2=1;A1=1;A0=1;B3=1;B2=1;B1=0;B0=1;
        #5 A3=0;A2=1;A1=1;A0=1;B3=1;B2=1;B1=1;B0=0;
        #5 A3=0;A2=1;A1=1;A0=1;B3=1;B2=1;B1=1;B0=1;
        #5 A3=1;A2=0;A1=0;A0=0;B3=0;B2=0;B1=0;B0=0;
        #5 A3=1;A2=0;A1=0;A0=0;B3=0;B2=0;B1=0;B0=1;
        #5 A3=1;A2=0;A1=0;A0=0;B3=0;B2=0;B1=1;B0=0;
        #5 A3=1;A2=0;A1=0;A0=0;B3=0;B2=0;B1=1;B0=1;
        #5 A3=1;A2=0;A1=0;A0=0;B3=0;B2=1;B1=0;B0=0;
        #5 A3=1;A2=0;A1=0;A0=0;B3=0;B2=1;B1=0;B0=1;
        #5 A3=1;A2=0;A1=0;A0=0;B3=0;B2=1;B1=1;B0=0;
        #5 A3=1;A2=0;A1=0;A0=0;B3=0;B2=1;B1=1;B0=1;
        #5 A3=1;A2=0;A1=0;A0=0;B3=1;B2=0;B1=0;B0=0;
        #5 A3=1;A2=0;A1=0;A0=0;B3=1;B2=0;B1=0;B0=1;
        #5 A3=1;A2=0;A1=0;A0=0;B3=1;B2=0;B1=1;B0=0;
        #5 A3=1;A2=0;A1=0;A0=0;B3=1;B2=0;B1=1;B0=1;
        #5 A3=1;A2=0;A1=0;A0=0;B3=1;B2=1;B1=0;B0=0;
        #5 A3=1;A2=0;A1=0;A0=0;B3=1;B2=1;B1=0;B0=1;
        #5 A3=1;A2=0;A1=0;A0=0;B3=1;B2=1;B1=1;B0=0;
        #5 A3=1;A2=0;A1=0;A0=0;B3=1;B2=1;B1=1;B0=1;
        #5 A3=1;A2=0;A1=0;A0=1;B3=0;B2=0;B1=0;B0=0;
        #5 A3=1;A2=0;A1=0;A0=1;B3=0;B2=0;B1=0;B0=1;
        #5 A3=1;A2=0;A1=0;A0=1;B3=0;B2=0;B1=1;B0=0;
        #5 A3=1;A2=0;A1=0;A0=1;B3=0;B2=0;B1=1;B0=1;
        #5 A3=1;A2=0;A1=0;A0=1;B3=0;B2=1;B1=0;B0=0;
        #5 A3=1;A2=0;A1=0;A0=1;B3=0;B2=1;B1=0;B0=1;
        #5 A3=1;A2=0;A1=0;A0=1;B3=0;B2=1;B1=1;B0=0;
        #5 A3=1;A2=0;A1=0;A0=1;B3=0;B2=1;B1=1;B0=1;
        #5 A3=1;A2=0;A1=0;A0=1;B3=1;B2=0;B1=0;B0=0;
        #5 A3=1;A2=0;A1=0;A0=1;B3=1;B2=0;B1=0;B0=1;
        #5 A3=1;A2=0;A1=0;A0=1;B3=1;B2=0;B1=1;B0=0;
        #5 A3=1;A2=0;A1=0;A0=1;B3=1;B2=0;B1=1;B0=1;
        #5 A3=1;A2=0;A1=0;A0=1;B3=1;B2=1;B1=0;B0=0;
        #5 A3=1;A2=0;A1=0;A0=1;B3=1;B2=1;B1=0;B0=1;
        #5 A3=1;A2=0;A1=0;A0=1;B3=1;B2=1;B1=1;B0=0;
        #5 A3=1;A2=0;A1=0;A0=1;B3=1;B2=1;B1=1;B0=1;
        #5 A3=1;A2=0;A1=1;A0=0;B3=0;B2=0;B1=0;B0=0;
        #5 A3=1;A2=0;A1=1;A0=0;B3=0;B2=0;B1=0;B0=1;
        #5 A3=1;A2=0;A1=1;A0=0;B3=0;B2=0;B1=1;B0=0;
        #5 A3=1;A2=0;A1=1;A0=0;B3=0;B2=0;B1=1;B0=1;
        #5 A3=1;A2=0;A1=1;A0=0;B3=0;B2=1;B1=0;B0=0;
        #5 A3=1;A2=0;A1=1;A0=0;B3=0;B2=1;B1=0;B0=1;
        #5 A3=1;A2=0;A1=1;A0=0;B3=0;B2=1;B1=1;B0=0;
        #5 A3=1;A2=0;A1=1;A0=0;B3=0;B2=1;B1=1;B0=1;
        #5 A3=1;A2=0;A1=1;A0=0;B3=1;B2=0;B1=0;B0=0;
        #5 A3=1;A2=0;A1=1;A0=0;B3=1;B2=0;B1=0;B0=1;
        #5 A3=1;A2=0;A1=1;A0=0;B3=1;B2=0;B1=1;B0=0;
        #5 A3=1;A2=0;A1=1;A0=0;B3=1;B2=0;B1=1;B0=1;
        #5 A3=1;A2=0;A1=1;A0=0;B3=1;B2=1;B1=0;B0=0;
        #5 A3=1;A2=0;A1=1;A0=0;B3=1;B2=1;B1=0;B0=1;
        #5 A3=1;A2=0;A1=1;A0=0;B3=1;B2=1;B1=1;B0=0;
        #5 A3=1;A2=0;A1=1;A0=0;B3=1;B2=1;B1=1;B0=1;
        #5 A3=1;A2=0;A1=1;A0=1;B3=0;B2=0;B1=0;B0=0;
        #5 A3=1;A2=0;A1=1;A0=1;B3=0;B2=0;B1=0;B0=1;
        #5 A3=1;A2=0;A1=1;A0=1;B3=0;B2=0;B1=1;B0=0;
        #5 A3=1;A2=0;A1=1;A0=1;B3=0;B2=0;B1=1;B0=1;
        #5 A3=1;A2=0;A1=1;A0=1;B3=0;B2=1;B1=0;B0=0;
        #5 A3=1;A2=0;A1=1;A0=1;B3=0;B2=1;B1=0;B0=1;
        #5 A3=1;A2=0;A1=1;A0=1;B3=0;B2=1;B1=1;B0=0;
        #5 A3=1;A2=0;A1=1;A0=1;B3=0;B2=1;B1=1;B0=1;
        #5 A3=1;A2=0;A1=1;A0=1;B3=1;B2=0;B1=0;B0=0;
        #5 A3=1;A2=0;A1=1;A0=1;B3=1;B2=0;B1=0;B0=1;
        #5 A3=1;A2=0;A1=1;A0=1;B3=1;B2=0;B1=1;B0=0;
        #5 A3=1;A2=0;A1=1;A0=1;B3=1;B2=0;B1=1;B0=1;
        #5 A3=1;A2=0;A1=1;A0=1;B3=1;B2=1;B1=0;B0=0;
        #5 A3=1;A2=0;A1=1;A0=1;B3=1;B2=1;B1=0;B0=1;
        #5 A3=1;A2=0;A1=1;A0=1;B3=1;B2=1;B1=1;B0=0;
        #5 A3=1;A2=0;A1=1;A0=1;B3=1;B2=1;B1=1;B0=1;
        #5 A3=1;A2=1;A1=0;A0=0;B3=0;B2=0;B1=0;B0=0;
        #5 A3=1;A2=1;A1=0;A0=0;B3=0;B2=0;B1=0;B0=1;
        #5 A3=1;A2=1;A1=0;A0=0;B3=0;B2=0;B1=1;B0=0;
        #5 A3=1;A2=1;A1=0;A0=0;B3=0;B2=0;B1=1;B0=1;
        #5 A3=1;A2=1;A1=0;A0=0;B3=0;B2=1;B1=0;B0=0;
        #5 A3=1;A2=1;A1=0;A0=0;B3=0;B2=1;B1=0;B0=1;
        #5 A3=1;A2=1;A1=0;A0=0;B3=0;B2=1;B1=1;B0=0;
        #5 A3=1;A2=1;A1=0;A0=0;B3=0;B2=1;B1=1;B0=1;
        #5 A3=1;A2=1;A1=0;A0=0;B3=1;B2=0;B1=0;B0=0;
        #5 A3=1;A2=1;A1=0;A0=0;B3=1;B2=0;B1=0;B0=1;
        #5 A3=1;A2=1;A1=0;A0=0;B3=1;B2=0;B1=1;B0=0;
        #5 A3=1;A2=1;A1=0;A0=0;B3=1;B2=0;B1=1;B0=1;
        #5 A3=1;A2=1;A1=0;A0=0;B3=1;B2=1;B1=0;B0=0;
        #5 A3=1;A2=1;A1=0;A0=0;B3=1;B2=1;B1=0;B0=1;
        #5 A3=1;A2=1;A1=0;A0=0;B3=1;B2=1;B1=1;B0=0;
        #5 A3=1;A2=1;A1=0;A0=0;B3=1;B2=1;B1=1;B0=1;
        #5 A3=1;A2=1;A1=0;A0=1;B3=0;B2=0;B1=0;B0=0;
        #5 A3=1;A2=1;A1=0;A0=1;B3=0;B2=0;B1=0;B0=1;
        #5 A3=1;A2=1;A1=0;A0=1;B3=0;B2=0;B1=1;B0=0;
        #5 A3=1;A2=1;A1=0;A0=1;B3=0;B2=0;B1=1;B0=1;
        #5 A3=1;A2=1;A1=0;A0=1;B3=0;B2=1;B1=0;B0=0;
        #5 A3=1;A2=1;A1=0;A0=1;B3=0;B2=1;B1=0;B0=1;
        #5 A3=1;A2=1;A1=0;A0=1;B3=0;B2=1;B1=1;B0=0;
        #5 A3=1;A2=1;A1=0;A0=1;B3=0;B2=1;B1=1;B0=1;
        #5 A3=1;A2=1;A1=0;A0=1;B3=1;B2=0;B1=0;B0=0;
        #5 A3=1;A2=1;A1=0;A0=1;B3=1;B2=0;B1=0;B0=1;
        #5 A3=1;A2=1;A1=0;A0=1;B3=1;B2=0;B1=1;B0=0;
        #5 A3=1;A2=1;A1=0;A0=1;B3=1;B2=0;B1=1;B0=1;
        #5 A3=1;A2=1;A1=0;A0=1;B3=1;B2=1;B1=0;B0=0;
        #5 A3=1;A2=1;A1=0;A0=1;B3=1;B2=1;B1=0;B0=1;
        #5 A3=1;A2=1;A1=0;A0=1;B3=1;B2=1;B1=1;B0=0;
        #5 A3=1;A2=1;A1=0;A0=1;B3=1;B2=1;B1=1;B0=1;
        #5 A3=1;A2=1;A1=1;A0=0;B3=0;B2=0;B1=0;B0=0;
        #5 A3=1;A2=1;A1=1;A0=0;B3=0;B2=0;B1=0;B0=1;
        #5 A3=1;A2=1;A1=1;A0=0;B3=0;B2=0;B1=1;B0=0;
        #5 A3=1;A2=1;A1=1;A0=0;B3=0;B2=0;B1=1;B0=1;
        #5 A3=1;A2=1;A1=1;A0=0;B3=0;B2=1;B1=0;B0=0;
        #5 A3=1;A2=1;A1=1;A0=0;B3=0;B2=1;B1=0;B0=1;
        #5 A3=1;A2=1;A1=1;A0=0;B3=0;B2=1;B1=1;B0=0;
        #5 A3=1;A2=1;A1=1;A0=0;B3=0;B2=1;B1=1;B0=1;
        #5 A3=1;A2=1;A1=1;A0=0;B3=1;B2=0;B1=0;B0=0;
        #5 A3=1;A2=1;A1=1;A0=0;B3=1;B2=0;B1=0;B0=1;
        #5 A3=1;A2=1;A1=1;A0=0;B3=1;B2=0;B1=1;B0=0;
        #5 A3=1;A2=1;A1=1;A0=0;B3=1;B2=0;B1=1;B0=1;
        #5 A3=1;A2=1;A1=1;A0=0;B3=1;B2=1;B1=0;B0=0;
        #5 A3=1;A2=1;A1=1;A0=0;B3=1;B2=1;B1=0;B0=1;
        #5 A3=1;A2=1;A1=1;A0=0;B3=1;B2=1;B1=1;B0=0;
        #5 A3=1;A2=1;A1=1;A0=0;B3=1;B2=1;B1=1;B0=1;
        #5 A3=1;A2=1;A1=1;A0=1;B3=0;B2=0;B1=0;B0=0;
        #5 A3=1;A2=1;A1=1;A0=1;B3=0;B2=0;B1=0;B0=1;
        #5 A3=1;A2=1;A1=1;A0=1;B3=0;B2=0;B1=1;B0=0;
        #5 A3=1;A2=1;A1=1;A0=1;B3=0;B2=0;B1=1;B0=1;
        #5 A3=1;A2=1;A1=1;A0=1;B3=0;B2=1;B1=0;B0=0;
        #5 A3=1;A2=1;A1=1;A0=1;B3=0;B2=1;B1=0;B0=1;
        #5 A3=1;A2=1;A1=1;A0=1;B3=0;B2=1;B1=1;B0=0;
        #5 A3=1;A2=1;A1=1;A0=1;B3=0;B2=1;B1=1;B0=1;
        #5 A3=1;A2=1;A1=1;A0=1;B3=1;B2=0;B1=0;B0=0;
        #5 A3=1;A2=1;A1=1;A0=1;B3=1;B2=0;B1=0;B0=1;
        #5 A3=1;A2=1;A1=1;A0=1;B3=1;B2=0;B1=1;B0=0;
        #5 A3=1;A2=1;A1=1;A0=1;B3=1;B2=0;B1=1;B0=1;
        #5 A3=1;A2=1;A1=1;A0=1;B3=1;B2=1;B1=0;B0=0;
        #5 A3=1;A2=1;A1=1;A0=1;B3=1;B2=1;B1=0;B0=1;
        #5 A3=1;A2=1;A1=1;A0=1;B3=1;B2=1;B1=1;B0=0;
        #5 A3=1;A2=1;A1=1;A0=1;B3=1;B2=1;B1=1;B0=1;
        #5 $finish;
    end 
endmodule

Verilog/AND/and_4bit_out.vcd
$date
	Fri Oct 27 11:44:28 2023
$end
$version
	Icarus Verilog
$end
$timescale
	1s
$end
$scope module and_4bit_tb $end
$scope module and_4bit_tb $end
$var wire 1 ! A0 $end
$var wire 1 " A1 $end
$var wire 1 # A2 $end
$var wire 1 $ A3 $end
$var wire 1 % B0 $end
$var wire 1 & B1 $end
$var wire 1 ' B2 $end
$var wire 1 ( B3 $end
$var wire 1 ) out0 $end
$var wire 1 * out1 $end
$var wire 1 + out2 $end
$var wire 1 , out3 $end
$upscope $end
$upscope $end
$enddefinitions $end
#0
$dumpvars
x,
x+
x*
x)
x(
x'
x&
x%
x$
x#
x"
x!
$end
#5
0)
0*
0+
0,
0%
0&
0'
0(
0!
0"
0#
0$
#10
1%
#15
0%
1&
#20
1%
#25
0%
0&
1'
#30
1%
#35
0%
1&
#40
1%
#45
0%
0&
0'
1(
#50
1%
#55
0%
1&
#60
1%
#65
0%
0&
1'
#70
1%
#75
0%
1&
#80
1%
#85
0%
0&
0'
0(
1!
#90
1)
1%
#95
0)
0%
1&
#100
1)
1%
#105
0)
0%
0&
1'
#110
1)
1%
#115
0)
0%
1&
#120
1)
1%
#125
0)
0%
0&
0'
1(
#130
1)
1%
#135
0)
0%
1&
#140
1)
1%
#145
0)
0%
0&
1'
#150
1)
1%
#155
0)
0%
1&
#160
1)
1%
#165
0)
0%
0&
0'
0(
0!
1"
#170
1%
#175
1*
0%
1&
#180
1%
#185
0*
0%
0&
1'
#190
1%
#195
1*
0%
1&
#200
1%
#205
0*
0%
0&
0'
1(
#210
1%
#215
1*
0%
1&
#220
1%
#225
0*
0%
0&
1'
#230
1%
#235
1*
0%
1&
#240
1%
#245
0*
0%
0&
0'
0(
1!
#250
1)
1%
#255
0)
1*
0%
1&
#260
1)
1%
#265
0)
0*
0%
0&
1'
#270
1)
1%
#275
0)
1*
0%
1&
#280
1)
1%
#285
0)
0*
0%
0&
0'
1(
#290
1)
1%
#295
0)
1*
0%
1&
#300
1)
1%
#305
0)
0*
0%
0&
1'
#310
1)
1%
#315
0)
1*
0%
1&
#320
1)
1%
#325
0)
0*
0%
0&
0'
0(
0!
0"
1#
#330
1%
#335
0%
1&
#340
1%
#345
1+
0%
0&
1'
#350
1%
#355
0%
1&
#360
1%
#365
0+
0%
0&
0'
1(
#370
1%
#375
0%
1&
#380
1%
#385
1+
0%
0&
1'
#390
1%
#395
0%
1&
#400
1%
#405
0+
0%
0&
0'
0(
1!
#410
1)
1%
#415
0)
0%
1&
#420
1)
1%
#425
0)
1+
0%
0&
1'
#430
1)
1%
#435
0)
0%
1&
#440
1)
1%
#445
0)
0+
0%
0&
0'
1(
#450
1)
1%
#455
0)
0%
1&
#460
1)
1%
#465
0)
1+
0%
0&
1'
#470
1)
1%
#475
0)
0%
1&
#480
1)
1%
#485
0+
0)
0%
0&
0'
0(
0!
1"
#490
1%
#495
1*
0%
1&
#500
1%
#505
0*
1+
0%
0&
1'
#510
1%
#515
1*
0%
1&
#520
1%
#525
0*
0+
0%
0&
0'
1(
#530
1%
#535
1*
0%
1&
#540
1%
#545
0*
1+
0%
0&
1'
#550
1%
#555
1*
0%
1&
#560
1%
#565
0*
0+
0%
0&
0'
0(
1!
#570
1)
1%
#575
0)
1*
0%
1&
#580
1)
1%
#585
0)
0*
1+
0%
0&
1'
#590
1)
1%
#595
0)
1*
0%
1&
#600
1)
1%
#605
0)
0*
0+
0%
0&
0'
1(
#610
1)
1%
#615
0)
1*
0%
1&
#620
1)
1%
#625
0)
0*
1+
0%
0&
1'
#630
1)
1%
#635
0)
1*
0%
1&
#640
1)
1%
#645
0)
0*
0+
0%
0&
0'
0(
0!
0"
0#
1$
#650
1%
#655
0%
1&
#660
1%
#665
0%
0&
1'
#670
1%
#675
0%
1&
#680
1%
#685
1,
0%
0&
0'
1(
#690
1%
#695
0%
1&
#700
1%
#705
0%
0&
1'
#710
1%
#715
0%
1&
#720
1%
#725
0,
0%
0&
0'
0(
1!
#730
1)
1%
#735
0)
0%
1&
#740
1)
1%
#745
0)
0%
0&
1'
#750
1)
1%
#755
0)
0%
1&
#760
1)
1%
#765
0)
1,
0%
0&
0'
1(
#770
1)
1%
#775
0)
0%
1&
#780
1)
1%
#785
0)
0%
0&
1'
#790
1)
1%
#795
0)
0%
1&
#800
1)
1%
#805
0,
0)
0%
0&
0'
0(
0!
1"
#810
1%
#815
1*
0%
1&
#820
1%
#825
0*
0%
0&
1'
#830
1%
#835
1*
0%
1&
#840
1%
#845
0*
1,
0%
0&
0'
1(
#850
1%
#855
1*
0%
1&
#860
1%
#865
0*
0%
0&
1'
#870
1%
#875
1*
0%
1&
#880
1%
#885
0*
0,
0%
0&
0'
0(
1!
#890
1)
1%
#895
0)
1*
0%
1&
#900
1)
1%
#905
0)
0*
0%
0&
1'
#910
1)
1%
#915
0)
1*
0%
1&
#920
1)
1%
#925
0)
0*
1,
0%
0&
0'
1(
#930
1)
1%
#935
0)
1*
0%
1&
#940
1)
1%
#945
0)
0*
0%
0&
1'
#950
1)
1%
#955
0)
1*
0%
1&
#960
1)
1%
#965
0,
0)
0*
0%
0&
0'
0(
0!
0"
1#
#970
1%
#975
0%
1&
#980
1%
#985
1+
0%
0&
1'
#990
1%
#995
0%
1&
#1000
1%
#1005
0+
1,
0%
0&
0'
1(
#1010
1%
#1015
0%
1&
#1020
1%
#1025
1+
0%
0&
1'
#1030
1%
#1035
0%
1&
#1040
1%
#1045
0+
0,
0%
0&
0'
0(
1!
#1050
1)
1%
#1055
0)
0%
1&
#1060
1)
1%
#1065
0)
1+
0%
0&
1'
#1070
1)
1%
#1075
0)
0%
1&
#1080
1)
1%
#1085
0)
0+
1,
0%
0&
0'
1(
#1090
1)
1%
#1095
0)
0%
1&
#1100
1)
1%
#1105
0)
1+
0%
0&
1'
#1110
1)
1%
#1115
0)
0%
1&
#1120
1)
1%
#1125
0+
0,
0)
0%
0&
0'
0(
0!
1"
#1130
1%
